saasready/__init__.py
saasready/audit.py
saasready/auth.py
saasready/client.py
saasready/errors.py
saasready/flags.py
saasready/models.py
saasready/orgs.py
saasready/rbac.py
saasready/session.py
saasready/users.py
saasready/utils.py
saasready-1.0.0.dist-info/METADATA
saasready-1.0.0.dist-info/WHEEL
saasready-1.0.0.dist-info/top_level.txt
saasready-1.0.0.dist-info/RECORD
