Metadata-Version: 2.4
Name: saasready
Version: 1.0.0
Summary: Enterprise-grade authentication and multi-tenancy SDK for Python
Home-page: https://github.com/yourusername/saasready
Author: SaaSReady Team
Author-email: SaaSReady Team <support@saasready.com>
Maintainer-email: SaaSReady Team <support@saasready.com>
License: MIT
Project-URL: Homepage, https://github.com/yourusername/saasready
Project-URL: Documentation, https://docs.saasready.com
Project-URL: Repository, https://github.com/yourusername/saasready
Project-URL: Bug Reports, https://github.com/yourusername/saasready/issues
Project-URL: Changelog, https://github.com/yourusername/saasready/blob/main/CHANGELOG.md
Keywords: authentication,authorization,saas,multi-tenancy,rbac,jwt,oauth,identity,access-control,enterprise-auth
Classifier: Development Status :: 5 - Production/Stable
Classifier: Intended Audience :: Developers
Classifier: License :: OSI Approved :: MIT License
Classifier: Programming Language :: Python :: 3
Classifier: Programming Language :: Python :: 3.8
Classifier: Programming Language :: Python :: 3.9
Classifier: Programming Language :: Python :: 3.10
Classifier: Programming Language :: Python :: 3.11
Classifier: Programming Language :: Python :: 3.12
Classifier: Operating System :: OS Independent
Classifier: Topic :: Software Development :: Libraries :: Python Modules
Classifier: Topic :: Internet :: WWW/HTTP
Classifier: Topic :: Security
Classifier: Topic :: System :: Systems Administration :: Authentication/Directory
Requires-Python: >=3.8
Requires-Dist: requests<3.0.0,>=2.25.0
Requires-Dist: pydantic<3.0.0,>=2.0.0
Requires-Dist: python-dateutil<3.0.0,>=2.8.0
Provides-Extra: dev
Requires-Dist: pytest>=7.0.0; extra == "dev"
Requires-Dist: pytest-cov>=4.0.0; extra == "dev"
Requires-Dist: pytest-mock>=3.10.0; extra == "dev"
Requires-Dist: black>=23.0.0; extra == "dev"
Requires-Dist: flake8>=6.0.0; extra == "dev"
Requires-Dist: mypy>=1.0.0; extra == "dev"
Requires-Dist: isort>=5.12.0; extra == "dev"
Requires-Dist: pre-commit>=3.0.0; extra == "dev"
Requires-Dist: tox>=4.0.0; extra == "dev"
Requires-Dist: build>=0.10.0; extra == "dev"
Requires-Dist: twine>=4.0.0; extra == "dev"
Requires-Dist: wheel>=0.40.0; extra == "dev"
Requires-Dist: responses>=0.23.0; extra == "dev"
Requires-Dist: faker>=18.0.0; extra == "dev"
Provides-Extra: docs
Requires-Dist: sphinx>=6.0.0; extra == "docs"
Requires-Dist: sphinx-rtd-theme>=1.2.0; extra == "docs"
Requires-Dist: sphinx-autodoc-typehints>=1.22.0; extra == "docs"
Provides-Extra: async
Requires-Dist: httpx>=0.24.0; extra == "async"
Requires-Dist: aiohttp>=3.8.0; extra == "async"
Dynamic: author
Dynamic: home-page
Dynamic: requires-python
